{"name": "The Grill Restaurant & Lounge", "rating": 5.0, "address": "Semiramis Intercontinental Cairo Hotel, Corniche El Nil", "image_url": "https://s3-eu-west-1.amazonaws.com/elmenusv5-stg/Normal/dc5862e2-2580-11e8-add5-0242ac110011.jpg", "phone": "0227988000,0227988188", "categories": {"Cold Appetizers": ["Peruvian Quinoa Salad (optional vegetarian), 105 EGP", "Seared Fresh Tuna Salad Nicoise, 100 EGP", "Combination Of, 130 EGP", "Classical Caesar Salad (on the table), 75 EGP", "Steamed Alaskan King Crab Leg Meat, 195 EGP", "Hand Cut Beef Steak Tartar (on the table), 135 EGP"], "Hot Appetizers": ["Oven Baked Bone Marrow, 75 EGP", "Gambos Ala Ajillo, 155 EGP", "Gratinated Chilean Mussels, 105 EGP", "Hand Crafted Ravioli, 105 EGP"], "Signatures": ["Pan-Fried French Foie Gras, 195 EGP", "Pan Seared Diver Sea Scallops, 130 EGP"], "Soups": ["Asparagus Cappuccino, 75 EGP", "Forest Mushroom Tea, 105 EGP", "Classical Gratinated, 75 EGP", "Foamy Green Garlic and Peas Soup, 75 EGP"], "Entree": ["French Magret de Canard, 195 EGP", "Seafood Platter, 310 EGP", "Fresh Out of the Oven, 155 EGP", "Pan-Roasted Patagonian Cod Fish, 225 EGP", "Duo of Beef and Veal Lucullus Fish, 235 EGP", "Lobster Tail to Your Liking, 310 EGP", "Oven Baked Salmon Coulibiac, 195 EGP"], "Specialty From The Grill": ["King Salmon Steak on the Bone, 220 EGP", "US Prime Fillet of Beef, 290 EGP", "US Prime Sirloin, 260 EGP", "US Rib Eye, 330 EGP", "US T-Bone Steak, 370 EGP", "US Bonless Short Rib, 250 EGP", "Dutch Veal Paillard, 180 EGP", "Spring Chicken Breast, 145 EGP", "Australian Lamb Chops, 215 EGP", "Optional: From the Land and From the Sea, 185 EGP", "Optional: From the Land and From the Sea, 95 EGP"], "Wagyu Beef": ["Australian Wagyu Beef Rib Eye Roll, 590 EGP", "Australian Wagyu Beef Sirloin, 510 EGP"], "On The Bone": ["U.S. Chateaubriand, 475 EGP", "U.S. Cote du bouef, 425 EGP"], "Sauces": ["Special Crust and Rubs, 35 EGP", "Garlic &Thyme Crust, 30 EGP"], "Vegetables": ["Green Beans, 45 EGP", "Wild Field Mushrooms, 45 EGP", "Garlic and Parsley Bread, 45 EGP", "Sauteed Spinach, 45 EGP", "Coleslaw or Mixed Salad, 45 EGP"], "Starch": ["Sweet Potato Crisps, 45 EGP", "French Fries or Truffle Fries, 45 EGP", "Allumettes Potato, 45 EGP", "Pommes Pont Neuf, 45 EGP", "Mousseline Potato, 45 EGP"], "Vegetarian": ["Assorted Mesclun Leaves, 75 EGP", "Oven Baked Macaroni, 95 EGP", "Homemade Pasta, 105 EGP"], "Dessert": ["Tahitian Vanilla, 80 EGP", "Freshly Baked Dark, 75 EGP", "New York Style Cheesecake, 90 EGP", "Sticky Arabian date Pudding, 80 EGP", "Fresh Out of the Oven Baked, 75 EGP", "Vanilla and Lime Panna Cotta, 80 EGP", "Espresso Hazelnut Darquoise, 85 EGP", "Artisanal Cheese Platter, 90 EGP"], "From Our Trolley": ["Classic Crepes Suzette, 105 EGP", "Sabayon, 90 EGP", "Seasonal Fruit Flamb\u00e9, 105 EGP", "Selection of Ice Creams, 55 EGP", "Sherbets, 65 EGP"]}}