{"name": "Chicken & Pie", "rating": 0.0, "address": "Arabesque Mall, Shop B16, Beside Post Office", "image_url": "https://s3-eu-west-1.amazonaws.com/elmenusv5-stg/Normal/fce709c8-a3a8-11e8-b2ca-0242ac110002.jpg", "phone": "01061194472,01124810082,01229376364", "categories": {"Appetizers": [{"dish_name": "Green Salad", "description": "", "price": "15 EGP", "image_URL": "https://mamadips.com/wp-content/uploads/2016/11/defimage.gif"}, {"dish_name": "Fattoush", "description": "", "price": "20 EGP", "image_URL": "https://mamadips.com/wp-content/uploads/2016/11/defimage.gif"}, {"dish_name": "Tabbouleh", "description": "", "price": "20 EGP", "image_URL": "https://mamadips.com/wp-content/uploads/2016/11/defimage.gif"}, {"dish_name": "Coleslaw", "description": "", "price": "15 EGP", "image_URL": "https://mamadips.com/wp-content/uploads/2016/11/defimage.gif"}, {"dish_name": "Messahbah", "description": "", "price": "15 EGP", "image_URL": "https://mamadips.com/wp-content/uploads/2016/11/defimage.gif"}, {"dish_name": "Moutabel", "description": "", "price": "15 EGP", "image_URL": "https://mamadips.com/wp-content/uploads/2016/11/defimage.gif"}, {"dish_name": "Tehina", "description": "", "price": "8 EGP", "image_URL": "https://mamadips.com/wp-content/uploads/2016/11/defimage.gif"}, {"dish_name": "Garlic Dip", "description": "", "price": "8 EGP", "image_URL": "https://mamadips.com/wp-content/uploads/2016/11/defimage.gif"}, {"dish_name": "Fried Kobeba", "description": "", "price": "12 EGP", "image_URL": "https://mamadips.com/wp-content/uploads/2016/11/defimage.gif"}, {"dish_name": "Meat Sambosak", "description": "", "price": "7 EGP", "image_URL": "https://mamadips.com/wp-content/uploads/2016/11/defimage.gif"}, {"dish_name": "Cheese Sambosak", "description": "", "price": "7 EGP", "image_URL": "https://mamadips.com/wp-content/uploads/2016/11/defimage.gif"}, {"dish_name": "Fries Packet", "description": "", "price": "7 - 15 EGP", "image_URL": "https://mamadips.com/wp-content/uploads/2016/11/defimage.gif"}], "Sweet Feteer": [{"dish_name": "Boghasha", "description": "", "price": "21 - 32 EGP", "image_URL": "https://mamadips.com/wp-content/uploads/2016/11/defimage.gif"}, {"dish_name": "Custard", "description": "", "price": "23 - 40 EGP", "image_URL": "https://mamadips.com/wp-content/uploads/2016/11/defimage.gif"}, {"dish_name": "Cinnamon", "description": "", "price": "23 - 40 EGP", "image_URL": "https://mamadips.com/wp-content/uploads/2016/11/defimage.gif"}, {"dish_name": "Nuts", "description": "", "price": "38 - 55 EGP", "image_URL": "https://mamadips.com/wp-content/uploads/2016/11/defimage.gif"}, {"dish_name": "Meloky", "description": "", "price": "33 - 50 EGP", "image_URL": "https://mamadips.com/wp-content/uploads/2016/11/defimage.gif"}, {"dish_name": "Honey and Qeshta", "description": "", "price": "43 - 60 EGP", "image_URL": "https://mamadips.com/wp-content/uploads/2016/11/defimage.gif"}, {"dish_name": "Alexandria", "description": "", "price": "38 - 55 EGP", "image_URL": "https://mamadips.com/wp-content/uploads/2016/11/defimage.gif"}, {"dish_name": "Jam and Qeshta", "description": "", "price": "43 - 60 EGP", "image_URL": "https://mamadips.com/wp-content/uploads/2016/11/defimage.gif"}, {"dish_name": "Chocolate", "description": "", "price": "43 - 60 EGP", "image_URL": "https://mamadips.com/wp-content/uploads/2016/11/defimage.gif"}, {"dish_name": "Chocolate with Banana", "description": "", "price": "48 - 70 EGP", "image_URL": "https://mamadips.com/wp-content/uploads/2016/11/defimage.gif"}, {"dish_name": "Banana", "description": "", "price": "33 - 50 EGP", "image_URL": "https://mamadips.com/wp-content/uploads/2016/11/defimage.gif"}], "Italian Hawawshy": [{"dish_name": "Meat", "description": "", "price": "30 EGP", "image_URL": "https://mamadips.com/wp-content/uploads/2016/11/defimage.gif"}, {"dish_name": "Sojouk", "description": "", "price": "30 EGP", "image_URL": "https://mamadips.com/wp-content/uploads/2016/11/defimage.gif"}, {"dish_name": "Sausage", "description": "", "price": "30 EGP", "image_URL": "https://mamadips.com/wp-content/uploads/2016/11/defimage.gif"}, {"dish_name": "Pastrami", "description": "", "price": "30 EGP", "image_URL": "https://mamadips.com/wp-content/uploads/2016/11/defimage.gif"}, {"dish_name": "Chicken", "description": "", "price": "30 EGP", "image_URL": "https://mamadips.com/wp-content/uploads/2016/11/defimage.gif"}, {"dish_name": "Chicken Shawerma", "description": "", "price": "35 EGP", "image_URL": "https://mamadips.com/wp-content/uploads/2016/11/defimage.gif"}, {"dish_name": "Meat Shawerma", "description": "", "price": "40 EGP", "image_URL": "https://mamadips.com/wp-content/uploads/2016/11/defimage.gif"}, {"dish_name": "Shrimp", "description": "", "price": "45 EGP", "image_URL": "https://mamadips.com/wp-content/uploads/2016/11/defimage.gif"}, {"dish_name": "Seafood", "description": "", "price": "45 EGP", "image_URL": "https://mamadips.com/wp-content/uploads/2016/11/defimage.gif"}, {"dish_name": "Mix Cheese", "description": "", "price": "35 EGP", "image_URL": "https://mamadips.com/wp-content/uploads/2016/11/defimage.gif"}, {"dish_name": "Mix Meat", "description": "", "price": "35 EGP", "image_URL": "https://mamadips.com/wp-content/uploads/2016/11/defimage.gif"}, {"dish_name": "Chicken and Pie", "description": "", "price": "40 EGP", "image_URL": "https://mamadips.com/wp-content/uploads/2016/11/defimage.gif"}], "Pizza": [{"dish_name": "Margherita", "description": "", "price": "35 - 55 EGP", "image_URL": "https://mamadips.com/wp-content/uploads/2016/11/defimage.gif"}, {"dish_name": "Vegetable", "description": "", "price": "38 - 60 EGP", "image_URL": "https://mamadips.com/wp-content/uploads/2016/11/defimage.gif"}, {"dish_name": "Mix Cheese", "description": "", "price": "48 - 70 EGP", "image_URL": "https://mamadips.com/wp-content/uploads/2016/11/defimage.gif"}, {"dish_name": "Chicken", "description": "", "price": "51 - 72 EGP", "image_URL": "https://mamadips.com/wp-content/uploads/2016/11/defimage.gif"}, {"dish_name": "Smoked Turkey", "description": "", "price": "48 - 70 EGP", "image_URL": "https://mamadips.com/wp-content/uploads/2016/11/defimage.gif"}, {"dish_name": "Tuna Pieces", "description": "", "price": "48 - 70 EGP", "image_URL": "https://mamadips.com/wp-content/uploads/2016/11/defimage.gif"}, {"dish_name": "Shrimp", "description": "", "price": "58 - 80 EGP", "image_URL": "https://mamadips.com/wp-content/uploads/2016/11/defimage.gif"}, {"dish_name": "Seafood", "description": "", "price": "55 - 80 EGP", "image_URL": "https://mamadips.com/wp-content/uploads/2016/11/defimage.gif"}, {"dish_name": "Sojouk", "description": "", "price": "51 - 73 EGP", "image_URL": "https://mamadips.com/wp-content/uploads/2016/11/defimage.gif"}, {"dish_name": "Sausage", "description": "", "price": "48 - 70 EGP", "image_URL": "https://mamadips.com/wp-content/uploads/2016/11/defimage.gif"}, {"dish_name": "Minced Meat", "description": "", "price": "48 - 70 EGP", "image_URL": "https://mamadips.com/wp-content/uploads/2016/11/defimage.gif"}, {"dish_name": "Pastrami", "description": "", "price": "48 - 70 EGP", "image_URL": "https://mamadips.com/wp-content/uploads/2016/11/defimage.gif"}, {"dish_name": "Mix Meat", "description": "", "price": "53 - 75 EGP", "image_URL": "https://mamadips.com/wp-content/uploads/2016/11/defimage.gif"}, {"dish_name": "Chicken Shawerma", "description": "", "price": "48 - 70 EGP", "image_URL": "https://mamadips.com/wp-content/uploads/2016/11/defimage.gif"}, {"dish_name": "Meat Shawerma", "description": "", "price": "53 - 75 EGP", "image_URL": "https://mamadips.com/wp-content/uploads/2016/11/defimage.gif"}, {"dish_name": "Mix Shawerma", "description": "", "price": "48 - 70 EGP", "image_URL": "https://mamadips.com/wp-content/uploads/2016/11/defimage.gif"}, {"dish_name": "Mushroom", "description": "", "price": "43 - 63 EGP", "image_URL": "https://mamadips.com/wp-content/uploads/2016/11/defimage.gif"}, {"dish_name": "Pepperoni", "description": "", "price": "48 - 70 EGP", "image_URL": "https://mamadips.com/wp-content/uploads/2016/11/defimage.gif"}, {"dish_name": "Smoked", "description": "", "price": "48 - 70 EGP", "image_URL": "https://mamadips.com/wp-content/uploads/2016/11/defimage.gif"}, {"dish_name": "Chicken and Pie", "description": "", "price": "58 - 75 EGP", "image_URL": "https://mamadips.com/wp-content/uploads/2016/11/defimage.gif"}], "Western": [{"dish_name": "Fries Sandwich", "description": "", "price": "12 EGP", "image_URL": "https://mamadips.com/wp-content/uploads/2016/11/defimage.gif"}, {"dish_name": "Cheese Fries Sandwich", "description": "", "price": "15 EGP", "image_URL": "https://mamadips.com/wp-content/uploads/2016/11/defimage.gif"}, {"dish_name": "Crispy Sandwich", "description": "", "price": "35 EGP", "image_URL": "https://mamadips.com/wp-content/uploads/2016/11/defimage.gif"}, {"dish_name": "Shish Sandwich", "description": "", "price": "35 EGP", "image_URL": "https://mamadips.com/wp-content/uploads/2016/11/defimage.gif"}, {"dish_name": "Fajita Sandwich", "description": "", "price": "35 EGP", "image_URL": "https://mamadips.com/wp-content/uploads/2016/11/defimage.gif"}, {"dish_name": "Zinger Sandwich", "description": "", "price": "35 EGP", "image_URL": "https://mamadips.com/wp-content/uploads/2016/11/defimage.gif"}, {"dish_name": "Cripsy Meal", "description": "", "price": "55 EGP", "image_URL": "https://mamadips.com/wp-content/uploads/2016/11/defimage.gif"}, {"dish_name": "Shish Meal", "description": "", "price": "55 EGP", "image_URL": "https://mamadips.com/wp-content/uploads/2016/11/defimage.gif"}, {"dish_name": "Zinger Meal", "description": "", "price": "55 EGP", "image_URL": "https://mamadips.com/wp-content/uploads/2016/11/defimage.gif"}], "Shawerma Plates": [{"dish_name": "Chicken", "description": "Syrian bread", "price": "25 EGP", "image_URL": "https://mamadips.com/wp-content/uploads/2016/11/defimage.gif"}, {"dish_name": "Chicken", "description": "French bread", "price": "30 EGP", "image_URL": "https://mamadips.com/wp-content/uploads/2016/11/defimage.gif"}, {"dish_name": "Arabian Chicken Meal", "description": "", "price": "40 EGP", "image_URL": "https://mamadips.com/wp-content/uploads/2016/11/defimage.gif"}, {"dish_name": "Extra Arabian Chicken Meal", "description": "", "price": "45 EGP", "image_URL": "https://mamadips.com/wp-content/uploads/2016/11/defimage.gif"}, {"dish_name": "1/4 Kilo Chicken Shawerma", "description": "", "price": "50 EGP", "image_URL": "https://mamadips.com/wp-content/uploads/2016/11/defimage.gif"}, {"dish_name": "1/2 Kilo Chicken Shawerma", "description": "", "price": "95 EGP", "image_URL": "https://mamadips.com/wp-content/uploads/2016/11/defimage.gif"}, {"dish_name": "1 Kilo Chicken Shawerma", "description": "", "price": "180 EGP", "image_URL": "https://mamadips.com/wp-content/uploads/2016/11/defimage.gif"}, {"dish_name": "Extra Mozzarella and Mushroom Per Sandwich", "description": "", "price": "5 EGP", "image_URL": "https://mamadips.com/wp-content/uploads/2016/11/defimage.gif"}, {"dish_name": "Meat", "description": "Syrian bread", "price": "38 EGP", "image_URL": "https://mamadips.com/wp-content/uploads/2016/11/defimage.gif"}, {"dish_name": "Meat", "description": "French bread", "price": "42 EGP", "image_URL": "https://mamadips.com/wp-content/uploads/2016/11/defimage.gif"}, {"dish_name": "Arabian Meat Meal", "description": "", "price": "52 EGP", "image_URL": "https://mamadips.com/wp-content/uploads/2016/11/defimage.gif"}, {"dish_name": "Extra Arabian Meat Meal", "description": "", "price": "60 EGP", "image_URL": "https://mamadips.com/wp-content/uploads/2016/11/defimage.gif"}, {"dish_name": "1/4 Kilo Meat Shawerma", "description": "", "price": "65 EGP", "image_URL": "https://mamadips.com/wp-content/uploads/2016/11/defimage.gif"}, {"dish_name": "1/2 Kilo Meat Shawerma", "description": "", "price": "125 EGP", "image_URL": "https://mamadips.com/wp-content/uploads/2016/11/defimage.gif"}, {"dish_name": "1 Kilo Meat Shawerma", "description": "", "price": "240 EGP", "image_URL": "https://mamadips.com/wp-content/uploads/2016/11/defimage.gif"}, {"dish_name": "Extra Mozzarella and Mushroom Per Meal", "description": "", "price": "5 EGP", "image_URL": "https://mamadips.com/wp-content/uploads/2016/11/defimage.gif"}, {"dish_name": "Chicken Shawerma Fattah", "description": "", "price": "45 EGP", "image_URL": "https://mamadips.com/wp-content/uploads/2016/11/defimage.gif"}, {"dish_name": "Meat Shawerma Fattah", "description": "", "price": "55 EGP", "image_URL": "https://mamadips.com/wp-content/uploads/2016/11/defimage.gif"}, {"dish_name": "Mix Shawerma Fattah", "description": "", "price": "50 EGP", "image_URL": "https://mamadips.com/wp-content/uploads/2016/11/defimage.gif"}, {"dish_name": "Mix Shawerma", "description": "Syrian bread", "price": "30 EGP", "image_URL": "https://mamadips.com/wp-content/uploads/2016/11/defimage.gif"}, {"dish_name": "Mix Shawerma", "description": "French bread", "price": "35 EGP", "image_URL": "https://mamadips.com/wp-content/uploads/2016/11/defimage.gif"}, {"dish_name": "Extra Fries Per Sandwich", "description": "", "price": "3 EGP", "image_URL": "https://mamadips.com/wp-content/uploads/2016/11/defimage.gif"}], "Grilled Chicken and Broast": [{"dish_name": "Chicken Broast", "description": "8 pieces, fries, gralic dip, pickles and bread", "price": "120 EGP", "image_URL": "https://mamadips.com/wp-content/uploads/2016/11/defimage.gif"}, {"dish_name": "1/2 Chicken Broast", "description": "4 pieces, fries, gralic dip, pickles and bread", "price": "65 EGP", "image_URL": "https://mamadips.com/wp-content/uploads/2016/11/defimage.gif"}, {"dish_name": "1/4 Chicken Broast Thigh Meal", "description": "Fries, gralic dip, pickles and bread", "price": "32 EGP", "image_URL": "https://mamadips.com/wp-content/uploads/2016/11/defimage.gif"}, {"dish_name": "1/4 Chicken Broast Breast Meal", "description": "Fries, gralic dip, pickles and bread", "price": "35 EGP", "image_URL": "https://mamadips.com/wp-content/uploads/2016/11/defimage.gif"}, {"dish_name": "Broast Meal 3 Drumstick", "description": "Fries, gralic dip, pickles and bread", "price": "30 EGP", "image_URL": "https://mamadips.com/wp-content/uploads/2016/11/defimage.gif"}, {"dish_name": "Rice Plate", "description": "", "price": "15 EGP", "image_URL": "https://mamadips.com/wp-content/uploads/2016/11/defimage.gif"}, {"dish_name": "Grilled Chicken Machine", "description": "Fries, gralic dip, pickles and bread", "price": "120 EGP", "image_URL": "https://mamadips.com/wp-content/uploads/2016/11/defimage.gif"}, {"dish_name": "1/2 Grilled Chicken Machine", "description": "Fries, gralic dip, pickles and bread", "price": "65 EGP", "image_URL": "https://mamadips.com/wp-content/uploads/2016/11/defimage.gif"}, {"dish_name": "1/4 Grilled Chicken Thigh with Rice", "description": "Fries, gralic dip, pickles and bread", "price": "32 EGP", "image_URL": "https://mamadips.com/wp-content/uploads/2016/11/defimage.gif"}, {"dish_name": "1/4 Grilled Chicken Breast with Rice", "description": "Fries, gralic dip, pickles and bread", "price": "35 EGP", "image_URL": "https://mamadips.com/wp-content/uploads/2016/11/defimage.gif"}, {"dish_name": "Grilled Chicken Sandwich", "description": "Fries, gralic dip, pickles and bread", "price": "35 EGP", "image_URL": "https://mamadips.com/wp-content/uploads/2016/11/defimage.gif"}], "Chicken and Pie Meal": [{"dish_name": "Chicken and Pie Meal", "description": "Rice plate, chicken shawerm a, meat shawerma, shish tawook, 2 crispy pieces, fried kobeba, gralic dip, fries, pickels and bread", "price": "90 EGP", "image_URL": "https://mamadips.com/wp-content/uploads/2016/11/defimage.gif"}], "Savory Feteer": [{"dish_name": "Kiri", "description": "", "price": "48 - 70 EGP", "image_URL": "https://mamadips.com/wp-content/uploads/2016/11/defimage.gif"}, {"dish_name": "Mozzarella", "description": "", "price": "43 - 65 EGP", "image_URL": "https://mamadips.com/wp-content/uploads/2016/11/defimage.gif"}, {"dish_name": "Roomi Cheese", "description": "", "price": "43 - 65 EGP", "image_URL": "https://mamadips.com/wp-content/uploads/2016/11/defimage.gif"}, {"dish_name": "Mix Cheese", "description": "", "price": "53 - 75 EGP", "image_URL": "https://mamadips.com/wp-content/uploads/2016/11/defimage.gif"}, {"dish_name": "Minced Meat", "description": "", "price": "48 - 70 EGP", "image_URL": "https://mamadips.com/wp-content/uploads/2016/11/defimage.gif"}, {"dish_name": "Sojouk", "description": "", "price": "51 - 73 EGP", "image_URL": "https://mamadips.com/wp-content/uploads/2016/11/defimage.gif"}, {"dish_name": "Sausage", "description": "", "price": "48 - 70 EGP", "image_URL": "https://mamadips.com/wp-content/uploads/2016/11/defimage.gif"}, {"dish_name": "Pastrami", "description": "", "price": "48 - 70 EGP", "image_URL": "https://mamadips.com/wp-content/uploads/2016/11/defimage.gif"}, {"dish_name": "Mix Meat", "description": "", "price": "53 - 75 EGP", "image_URL": "https://mamadips.com/wp-content/uploads/2016/11/defimage.gif"}, {"dish_name": "Mushroom", "description": "", "price": "43 - 63 EGP", "image_URL": "https://mamadips.com/wp-content/uploads/2016/11/defimage.gif"}, {"dish_name": "Egg", "description": "", "price": "38 - 55 EGP", "image_URL": "https://mamadips.com/wp-content/uploads/2016/11/defimage.gif"}, {"dish_name": "Pieces of Tuna", "description": "", "price": "48 - 65 EGP", "image_URL": "https://mamadips.com/wp-content/uploads/2016/11/defimage.gif"}, {"dish_name": "Chicken", "description": "", "price": "51 - 73 EGP", "image_URL": "https://mamadips.com/wp-content/uploads/2016/11/defimage.gif"}, {"dish_name": "Chicken Shawerma", "description": "", "price": "53 - 75 EGP", "image_URL": "https://mamadips.com/wp-content/uploads/2016/11/defimage.gif"}, {"dish_name": "Meat Shawerma", "description": "", "price": "58 - 80 EGP", "image_URL": "https://mamadips.com/wp-content/uploads/2016/11/defimage.gif"}, {"dish_name": "Mix Shawerma", "description": "", "price": "58 - 75 EGP", "image_URL": "https://mamadips.com/wp-content/uploads/2016/11/defimage.gif"}, {"dish_name": "Smoked Turkey", "description": "", "price": "48 - 70 EGP", "image_URL": "https://mamadips.com/wp-content/uploads/2016/11/defimage.gif"}, {"dish_name": "Pepperoni", "description": "", "price": "48 - 70 EGP", "image_URL": "https://mamadips.com/wp-content/uploads/2016/11/defimage.gif"}, {"dish_name": "Shrimp", "description": "", "price": "58 - 80 EGP", "image_URL": "https://mamadips.com/wp-content/uploads/2016/11/defimage.gif"}, {"dish_name": "Seafood", "description": "", "price": "58 - 80 EGP", "image_URL": "https://mamadips.com/wp-content/uploads/2016/11/defimage.gif"}, {"dish_name": "Chicken and Pie", "description": "", "price": "58 - 80 EGP", "image_URL": "https://mamadips.com/wp-content/uploads/2016/11/defimage.gif"}, {"dish_name": "Extra Oriental", "description": "", "price": "10 - 15 EGP", "image_URL": "https://mamadips.com/wp-content/uploads/2016/11/defimage.gif"}], "Drinks": [{"dish_name": "Pepsi Can", "description": "", "price": "8 EGP", "image_URL": "https://mamadips.com/wp-content/uploads/2016/11/defimage.gif"}, {"dish_name": "1 Liter Pepsi", "description": "", "price": "10 EGP", "image_URL": "https://mamadips.com/wp-content/uploads/2016/11/defimage.gif"}, {"dish_name": "Small Water", "description": "", "price": "5 EGP", "image_URL": "https://mamadips.com/wp-content/uploads/2016/11/defimage.gif"}, {"dish_name": "Large Water", "description": "", "price": "7 EGP", "image_URL": "https://mamadips.com/wp-content/uploads/2016/11/defimage.gif"}, {"dish_name": "Smoothie", "description": "", "price": "10 EGP", "image_URL": "https://mamadips.com/wp-content/uploads/2016/11/defimage.gif"}, {"dish_name": "Ayran", "description": "", "price": "8 EGP", "image_URL": "https://mamadips.com/wp-content/uploads/2016/11/defimage.gif"}]}}