{"name": "Doner Kabab Grills", "rating": 0.0, "address": "El Mostasha El Italy Street, behind El Wayly Police Station", "image_url": "https://s3-eu-west-1.amazonaws.com/elmenusv5-stg/Normal/3f25482b-5ac5-4a7e-b339-8f6708402c81.jpg", "phone": "01028251188,01100028377", "categories": {"Grills": [{"dish_name": "Kilo Kabab", "description": "", "price": "250 EGP", "image_URL": "https://mamadips.com/wp-content/uploads/2016/11/defimage.gif"}, {"dish_name": "Kilo Mix Kabab", "description": "", "price": "220 EGP", "image_URL": "https://mamadips.com/wp-content/uploads/2016/11/defimage.gif"}, {"dish_name": "Kilo Lamb Kofta", "description": "", "price": "150 EGP", "image_URL": "https://mamadips.com/wp-content/uploads/2016/11/defimage.gif"}, {"dish_name": "Kilo Kunduz Kofta", "description": "", "price": "120 EGP", "image_URL": "https://mamadips.com/wp-content/uploads/2016/11/defimage.gif"}, {"dish_name": "Kilo Kunduz Tarb", "description": "", "price": "150 EGP", "image_URL": "https://mamadips.com/wp-content/uploads/2016/11/defimage.gif"}, {"dish_name": "Kilo Shish Tawook", "description": "", "price": "120 EGP", "image_URL": "https://mamadips.com/wp-content/uploads/2016/11/defimage.gif"}, {"dish_name": "Chicken Shish", "description": "", "price": "70 EGP", "image_URL": "https://mamadips.com/wp-content/uploads/2016/11/defimage.gif"}, {"dish_name": "Tikka Chicken", "description": "", "price": "70 EGP", "image_URL": "https://mamadips.com/wp-content/uploads/2016/11/defimage.gif"}], "Meals": [{"dish_name": "1/2 Chicken Shish", "description": "Rice, vegetables, salad, bread", "price": "45 EGP", "image_URL": "https://mamadips.com/wp-content/uploads/2016/11/defimage.gif"}, {"dish_name": "1/4 Shish Tawook", "description": "Rice, salad, bread", "price": "40 EGP", "image_URL": "https://mamadips.com/wp-content/uploads/2016/11/defimage.gif"}, {"dish_name": "1/4 Chicken Shish and 1/8 Kofta", "description": "Rice, vegetables, salad, bread", "price": "42 EGP", "image_URL": "https://mamadips.com/wp-content/uploads/2016/11/defimage.gif"}, {"dish_name": "1/4 Kofta", "description": "Rice, vegetables, salad, bread", "price": "40 EGP", "image_URL": "https://mamadips.com/wp-content/uploads/2016/11/defimage.gif"}, {"dish_name": "1/4 Chicken Shish", "description": "Rice, vegetables, salad, bread", "price": "27 EGP", "image_URL": "https://mamadips.com/wp-content/uploads/2016/11/defimage.gif"}], "Rice & Pasta": [{"dish_name": "Rice with Liver", "description": "", "price": "10 EGP", "image_URL": "https://mamadips.com/wp-content/uploads/2016/11/defimage.gif"}, {"dish_name": "Plain Rice", "description": "", "price": "5 EGP", "image_URL": "https://mamadips.com/wp-content/uploads/2016/11/defimage.gif"}, {"dish_name": "Pasta with Liver", "description": "", "price": "10 EGP", "image_URL": "https://mamadips.com/wp-content/uploads/2016/11/defimage.gif"}, {"dish_name": "Pasta with Minced Meat", "description": "", "price": "10 EGP", "image_URL": "https://mamadips.com/wp-content/uploads/2016/11/defimage.gif"}, {"dish_name": "Plain Pasta", "description": "", "price": "6 EGP", "image_URL": "https://mamadips.com/wp-content/uploads/2016/11/defimage.gif"}], "Sandwiches": [{"dish_name": "Charcoaled Kofta", "description": "", "price": "0 - 101 EGP", "image_URL": "https://mamadips.com/wp-content/uploads/2016/11/defimage.gif"}, {"dish_name": "Charcoaled Tarb", "description": "", "price": "18 EGP", "image_URL": "https://mamadips.com/wp-content/uploads/2016/11/defimage.gif"}, {"dish_name": "Shish Tawook", "description": "", "price": "18 EGP", "image_URL": "https://mamadips.com/wp-content/uploads/2016/11/defimage.gif"}, {"dish_name": "Charcoaled Hawawshi", "description": "", "price": "0 - 101 EGP", "image_URL": "https://mamadips.com/wp-content/uploads/2016/11/defimage.gif"}]}}