{"name": "Koshary Cairo", "rating": 0.0, "address": "Next to Radisson Blu Hotel", "image_url": "https://s3-eu-west-1.amazonaws.com/elmenusv5-stg/Normal/04ec4b5a-835a-4cb6-9d0a-25b10c9c1820.jpg", "phone": "01096800106,0222698606,0222698607", "categories": {"Appetizers & Salads": [{"dish_name": "Toasted Bread", "description": "", "price": "6 EGP", "image_URL": "https://mamadips.com/wp-content/uploads/2016/11/defimage.gif"}, {"dish_name": "Baladi Salad", "description": "", "price": "6 EGP", "image_URL": "https://mamadips.com/wp-content/uploads/2016/11/defimage.gif"}], "Koshary": [{"dish_name": "Cairo", "description": "", "price": "10 EGP", "image_URL": "https://mamadips.com/wp-content/uploads/2016/11/defimage.gif"}, {"dish_name": "Primo Cairo", "description": "", "price": "12 EGP", "image_URL": "https://mamadips.com/wp-content/uploads/2016/11/defimage.gif"}, {"dish_name": "Large Cairo", "description": "", "price": "14 EGP", "image_URL": "https://mamadips.com/wp-content/uploads/2016/11/defimage.gif"}, {"dish_name": "Super Cairo", "description": "", "price": "18 EGP", "image_URL": "https://mamadips.com/wp-content/uploads/2016/11/defimage.gif"}, {"dish_name": "Foil Primo", "description": "", "price": "12 EGP", "image_URL": "https://mamadips.com/wp-content/uploads/2016/11/defimage.gif"}, {"dish_name": "Medium Foil", "description": "", "price": "15 EGP", "image_URL": "https://mamadips.com/wp-content/uploads/2016/11/defimage.gif"}, {"dish_name": "Large Foil", "description": "", "price": "19 EGP", "image_URL": "https://mamadips.com/wp-content/uploads/2016/11/defimage.gif"}, {"dish_name": "Super Foil", "description": "", "price": "24 EGP", "image_URL": "https://mamadips.com/wp-content/uploads/2016/11/defimage.gif"}, {"dish_name": "Mega Foil", "description": "", "price": "40 EGP", "image_URL": "https://mamadips.com/wp-content/uploads/2016/11/defimage.gif"}, {"dish_name": "Family Foil", "description": "", "price": "65 EGP", "image_URL": "https://mamadips.com/wp-content/uploads/2016/11/defimage.gif"}], "Meals": [{"dish_name": "Medium Combo", "description": "Medium koshary, 1 salad, your choice of dessert", "price": "24 EGP", "image_URL": "https://mamadips.com/wp-content/uploads/2016/11/defimage.gif"}, {"dish_name": "Large Combo", "description": "Large koshary, 1 salad, your choice of dessert", "price": "28 EGP", "image_URL": "https://mamadips.com/wp-content/uploads/2016/11/defimage.gif"}, {"dish_name": "Super Combo", "description": "Super koshary, 1 salad, your choice of dessert", "price": "32 EGP", "image_URL": "https://mamadips.com/wp-content/uploads/2016/11/defimage.gif"}, {"dish_name": "Mega Combo", "description": "Mega koshary, toasted bread, salad, 2 desserts", "price": "60 EGP", "image_URL": "https://mamadips.com/wp-content/uploads/2016/11/defimage.gif"}, {"dish_name": "Family Combo", "description": "Family koshary, toasted bread, 2 salad, 3 desserts", "price": "92 EGP", "image_URL": "https://mamadips.com/wp-content/uploads/2016/11/defimage.gif"}], "Extras": [{"dish_name": "Salsa Packet", "description": "", "price": "4 EGP", "image_URL": "https://mamadips.com/wp-content/uploads/2016/11/defimage.gif"}, {"dish_name": "Salsa Box", "description": "", "price": "5 EGP", "image_URL": "https://mamadips.com/wp-content/uploads/2016/11/defimage.gif"}, {"dish_name": "Ta'lia", "description": "", "price": "5 EGP", "image_URL": "https://mamadips.com/wp-content/uploads/2016/11/defimage.gif"}, {"dish_name": "Hummus", "description": "", "price": "5 EGP", "image_URL": "https://mamadips.com/wp-content/uploads/2016/11/defimage.gif"}, {"dish_name": "Lentil", "description": "", "price": "5 EGP", "image_URL": "https://mamadips.com/wp-content/uploads/2016/11/defimage.gif"}, {"dish_name": "Shata and Daqa", "description": "", "price": "4 EGP", "image_URL": "https://mamadips.com/wp-content/uploads/2016/11/defimage.gif"}], "Desserts": [{"dish_name": "Rice Pudding", "description": "", "price": "8 EGP", "image_URL": "https://mamadips.com/wp-content/uploads/2016/11/defimage.gif"}, {"dish_name": "Milk Pudding", "description": "", "price": "8 EGP", "image_URL": "https://mamadips.com/wp-content/uploads/2016/11/defimage.gif"}], "Drinks": [{"dish_name": "Pepsi Can", "description": "", "price": "8 EGP", "image_URL": "https://mamadips.com/wp-content/uploads/2016/11/defimage.gif"}, {"dish_name": "Pepsi Diet Can", "description": "", "price": "8 EGP", "image_URL": "https://mamadips.com/wp-content/uploads/2016/11/defimage.gif"}, {"dish_name": "7up Can", "description": "", "price": "8 EGP", "image_URL": "https://mamadips.com/wp-content/uploads/2016/11/defimage.gif"}, {"dish_name": "7up Diet  Can", "description": "", "price": "8 EGP", "image_URL": "https://mamadips.com/wp-content/uploads/2016/11/defimage.gif"}, {"dish_name": "Mirinda", "description": "Fruits", "price": "8 EGP", "image_URL": "https://mamadips.com/wp-content/uploads/2016/11/defimage.gif"}, {"dish_name": "Small Mineral Water", "description": "", "price": "5 EGP", "image_URL": "https://mamadips.com/wp-content/uploads/2016/11/defimage.gif"}, {"dish_name": "Large Mineral Water", "description": "", "price": "8 EGP", "image_URL": "https://mamadips.com/wp-content/uploads/2016/11/defimage.gif"}]}}