{"name": "Koshary Cairo", "rating": 0.0, "address": "Next to Radisson Blu Hotel", "image_url": "https://s3-eu-west-1.amazonaws.com/elmenusv5-stg/Normal/04ec4b5a-835a-4cb6-9d0a-25b10c9c1820.jpg", "phone": "01096800106,0222698606,0222698607", "categories": {"Appetizers & Salads": ["Toasted Bread, 6 EGP", "Baladi Salad, 6 EGP"], "Koshary": ["Cairo, 10 EGP", "Primo Cairo, 12 EGP", "Large Cairo, 14 EGP", "Super Cairo, 18 EGP", "Foil Primo, 12 EGP", "Medium Foil, 15 EGP", "Large Foil, 19 EGP", "Super Foil, 24 EGP", "Mega Foil, 40 EGP", "Family Foil, 65 EGP"], "Meals": ["Medium Combo, 24 EGP", "Large Combo, 28 EGP", "Super Combo, 32 EGP", "Mega Combo, 60 EGP", "Family Combo, 92 EGP"], "Extras": ["Salsa Packet, 4 EGP", "Salsa Box, 5 EGP", "Ta'lia, 5 EGP", "Hummus, 5 EGP", "Lentil, 5 EGP", "Shata and Daqa, 4 EGP"], "Desserts": ["Rice Pudding, 8 EGP", "Milk Pudding, 8 EGP"], "Drinks": ["Pepsi Can, 8 EGP", "Pepsi Diet Can, 8 EGP", "7up Can, 8 EGP", "7up Diet  Can, 8 EGP", "Mirinda, 8 EGP", "Small Mineral Water, 5 EGP", "Large Mineral Water, 8 EGP"]}}